city_graph/__init__.py
city_graph/version.py
city_graph-0.1.dist-info/METADATA
city_graph-0.1.dist-info/WHEEL
city_graph-0.1.dist-info/top_level.txt
city_graph-0.1.dist-info/RECORD
